{
  "words": 3132,
  "comments": 65,
  "prs": {
    "opened": 8,
    "closed": 2,
    "words": 3075
  },
  "issues": {
    "opened": 0,
    "closed": 0,
    "words": 57
  },
  "activity": {
    "CTC": {"open":11},
    "Future-CI": {"open":5},
    "Intl": {"open":16},
    "LTS": {"open":28},
    "NG": {"open":28},
    "TSC": {"open":44},
    "api": {"open":12},
    "benchmarking": {"open":15},
    "build": {"open":104},
    "build-container-sync": {"open":1},
    "build-containers": {"open":1},
    "citgm": {"open":32},
    "code-and-learn": {"open":11},
    "collaboration": {"open":6},
    "contribution-slides": {"open":0},
    "dev-policy": {"open":33},
    "diagnostics": {"open":19},
    "doc-tool": {"open":2},
    "docker-iojs": {"open":5},
    "docker-node": {"open":20},
    "docs": {"open":50},
    "education": {
      "3": {"comments":3,"words":13,"pr":true},
      "open": 4,
      "words": 13,
      "comments": 3
    },
    "email": {
      "21": {"comments":0,"words":13,"pr":true,"opened":"2016-07-30T23:47:22Z","opener":"1141386"},
      "open": 1,
      "words": 13,
      "opened": 1
    },
    "evangelism": {"open":39},
    "foundation-slides": {"open":4},
    "foundation.nodejs.org": {"open":4},
    "hardware": {"open":13},
    "help": {
      "235": {"comments":9,"words":589,"opened":"2016-07-30T05:52:51Z","opener":"20158340","pr":true},
      "open": 71,
      "words": 589,
      "opened": 1,
      "comments": 9
    },
    "http": {"open":14},
    "http-parser": {"open":37},
    "inclusivity": {
      "146": {"comments":0,"words":0,"pr":true,"opened":"2016-07-30T23:44:22Z","opener":"1141386"},
      "open": 19,
      "words": 0,
      "opened": 1
    },
    "inclusivity-slack-inviter": {"open":1},
    "installer": {
      "26": {"comments":2,"words":65,"pr":true},
      "open": 17,
      "words": 65,
      "comments": 2
    },
    "iojs.org": {"open":9},
    "live.nodejs.org": {"open":12},
    "logos": {"open":0},
    "membership": {"open":2},
    "nan": {
      "595": {"comments":1,"words":67,"pr":true},
      "open": 21,
      "words": 67,
      "comments": 1
    },
    "node": {
      "854": {"comments":1,"words":62,"pr":true},
      "5599": {"comments":2,"words":67,"pr":true},
      "6601": {"comments":1,"words":18,"pr":true},
      "7767": {"comments":1,"words":18,"pr":true},
      "7829": {"comments":2,"words":8,"pr":true},
      "7831": {"comments":2,"words":34,"pr":true},
      "7854": {"comments":2,"words":35,"pr":true},
      "7857": {"comments":3,"words":94,"pr":true},
      "7859": {"comments":5,"words":74,"pr":true},
      "7863": {"comments":1,"words":39,"pr":true},
      "7893": {"comments":3,"words":156,"pr":true},
      "7894": {"comments":1,"words":13,"pr":true},
      "7895": {"comments":1,"words":20,"pr":true},
      "7906": {"comments":3,"words":18,"pr":true},
      "7908": {"comments":1,"words":10,"pr":true},
      "7918": {"comments":2,"words":237,"opened":"2016-07-30T03:42:02Z","opener":"20699254","pr":true,"closed":"","closer":"54666"},
      "7919": {"comments":0,"words":51,"opened":"2016-07-30T03:53:51Z","opener":"718899","pr":true},
      "7920": {"comments":6,"words":410,"pr":true,"opened":"2016-07-30T04:58:20Z","opener":"718899"},
      "7921": {"comments":2,"words":240,"opened":"2016-07-30T05:47:27Z","opener":"20158340","pr":true,"closed":"","closer":"291301"},
      "open": 755,
      "words": 1661,
      "opened": 4,
      "comments": 42,
      "closed": 2,
      "7764b6cb964ef8c481f3c348b76c6980e1e4f977": {"comments":3,"words":57,"pr":false}
    },
    "node-addon-examples": {"open":30},
    "node-chakracore": {"open":23},
    "node-convergence-archive": {"open":6},
    "node-eps": {"open":18},
    "node-gyp": {
      "809": {"comments":1,"words":272,"pr":true},
      "874": {"comments":1,"words":50,"pr":true},
      "1003": {"comments":1,"words":289,"opened":"2016-07-30T19:59:44Z","opener":"20266801","pr":true},
      "open": 220,
      "words": 611,
      "comments": 3,
      "opened": 1
    },
    "node-v0.x-archive": {
      "4666": {"comments":3,"words":99,"pr":true},
      "open": 615,
      "words": 99,
      "comments": 3
    },
    "nodejs-ar": {"open":1},
    "nodejs-bg": {"open":1},
    "nodejs-bn": {"open":1},
    "nodejs-cs": {"open":1},
    "nodejs-da": {"open":5},
    "nodejs-de": {"open":2},
    "nodejs-el": {"open":2},
    "nodejs-es": {"open":7},
    "nodejs-fa": {"open":1},
    "nodejs-fi": {"open":18},
    "nodejs-fr": {"open":21},
    "nodejs-he": {"open":2},
    "nodejs-hi": {"open":10},
    "nodejs-hu": {"open":3},
    "nodejs-id": {"open":6},
    "nodejs-it": {"open":3},
    "nodejs-ja": {"open":4},
    "nodejs-ka": {"open":7},
    "nodejs-ko": {
      "398": {"comments":2,"words":14,"pr":true},
      "open": 9,
      "words": 14,
      "comments": 2
    },
    "nodejs-mk": {"open":2},
    "nodejs-ms": {"open":1},
    "nodejs-nl": {"open":6},
    "nodejs-no": {"open":13},
    "nodejs-pl": {"open":1},
    "nodejs-pt": {"open":8},
    "nodejs-ro": {"open":3},
    "nodejs-ru": {"open":45},
    "nodejs-sv": {"open":1},
    "nodejs-sw": {"open":1},
    "nodejs-ta": {"open":1},
    "nodejs-tr": {"open":2},
    "nodejs-uk": {"open":43},
    "nodejs-vi": {"open":8},
    "nodejs-zh-CN": {"open":4},
    "nodejs-zh-TW": {"open":21},
    "nodejs.org": {"open":36},
    "nodejs.org-archive": {"open":12},
    "nodejs.org-new": {"open":2},
    "post-mortem": {"open":22},
    "promises": {"open":21},
    "readable-stream": {"open":27},
    "roadmap": {"open":15},
    "smoke-test": {"open":4},
    "summit": {"open":2},
    "testing": {"open":14},
    "v8": {"open":0},
    "vm": {"open":2}
  },
  "users": {
    "52195": {
      "id": "52195",
      "login": "mcollina",
      "words": {
        "node/comments/7764b6cb964ef8c481f3c348b76c6980e1e4f977#18460728": 8
      }
    },
    "54666": {
      "id": "54666",
      "login": "mscdex",
      "words": {
        "node/pulls/7918#236340345": 9
      }
    },
    "101553": {
      "id": "101553",
      "login": "fhinkel",
      "words": {
        "node/pulls/7863#236347262": 39,
        "node/pulls/7908#236347362": 10
      }
    },
    "262105": {
      "id": "262105",
      "login": "kahwee",
      "words": {
        "help/pulls/235#236353183": 54,
        "help/pulls/235#236354390": 9
      }
    },
    "275871": {
      "id": "275871",
      "login": "bnoordhuis",
      "words": {
        "node-v0.x-archive/pulls/4666#236352004": 57,
        "node/pulls/5599#236352245": 55,
        "nan/pulls/595#236352944": 67,
        "node-gyp/pulls/874#236353512": 50,
        "node/pulls/7893#236353844": 85,
        "node/pulls/7906#72884787": 13,
        "node/pulls/7906#236357028": 4,
        "node/pulls/7893#236387496": 23,
        "node-gyp/pulls/1003#236387660": 7,
        "node/pulls/7859#72893634": 5,
        "node/pulls/7859#72893643": 4,
        "node/pulls/7859#236387859": 8
      }
    },
    "291301": {
      "id": "291301",
      "login": "ChALkeR",
      "words": {
        "node/pulls/7921#236346123": 34
      }
    },
    "390146": {
      "id": "390146",
      "login": "outsideris",
      "words": {
        "nodejs-ko/pulls/398#72887017": 12,
        "nodejs-ko/pulls/398#236363663": 2
      }
    },
    "432351": {
      "id": "432351",
      "login": "danbev",
      "words": {
        "node/pulls/7893#236357406": 48
      }
    },
    "439929": {
      "id": "439929",
      "login": "jasnell",
      "words": {
        "node/pulls/7906#236380489": 1
      }
    },
    "479726": {
      "id": "479726",
      "login": "recursivefunk",
      "words": {
        "education/pulls/3#236329613": 6
      }
    },
    "718899": {
      "id": "718899",
      "login": "Trott",
      "words": {
        "node/issues/7919": 51,
        "node/pulls/7857#236339499": 63,
        "node/pulls/7920": 126,
        "node/pulls/5599#236343500": 12,
        "node/pulls/7767#236373461": 18,
        "node/pulls/7854#236386817": 31,
        "node/pulls/7920#72893646": 237,
        "node/pulls/7920#236388278": 13
      },
      "opened": [
        "node/issues/7919",
        "node/pulls/7920"
      ]
    },
    "980835": {
      "id": "980835",
      "login": "EugeneDae",
      "words": {
        "node/pulls/854#236374788": 62
      }
    },
    "1084056": {
      "id": "1084056",
      "login": "santigimeno",
      "words": {
        "node/pulls/7857#72886934": 7,
        "node/pulls/7857#236363770": 24,
        "node/pulls/7859#236373802": 46,
        "node/pulls/7859#236376440": 11,
        "node/pulls/7854#236382996": 4
      }
    },
    "1093990": {
      "id": "1093990",
      "login": "Fishrock123",
      "words": {
        "installer/pulls/26#236376668": 20
      }
    },
    "1141386": {
      "id": "1141386",
      "login": "nebrius",
      "words": {
        "inclusivity/pulls/146": 0,
        "email/pulls/21": 13
      },
      "opened": [
        "inclusivity/pulls/146",
        "email/pulls/21"
      ]
    },
    "1231635": {
      "id": "1231635",
      "login": "phillipj",
      "words": {
        "node/pulls/6601#236387230": 18
      }
    },
    "1449826": {
      "id": "1449826",
      "login": "micnic",
      "words": {
        "node/pulls/7831#236356269": 19
      }
    },
    "1519700": {
      "id": "1519700",
      "login": "shirazz",
      "words": {
        "education/pulls/3#236339747": 4
      }
    },
    "1622515": {
      "id": "1622515",
      "login": "princejwesley",
      "words": {
        "node/pulls/7918#236340336": 46,
        "node/pulls/7829#236378686": 2
      }
    },
    "1658779": {
      "id": "1658779",
      "login": "rizvankukad",
      "words": {
        "education/pulls/3#236342949": 3
      }
    },
    "1935767": {
      "id": "1935767",
      "login": "yorkie",
      "words": {
        "node/pulls/7831#236354720": 15,
        "node/pulls/7894#72884563": 13,
        "node/pulls/7829#236379284": 6
      }
    },
    "2096101": {
      "id": "2096101",
      "login": "Kikobeats",
      "words": {
        "node/comments/7764b6cb964ef8c481f3c348b76c6980e1e4f977#18460722": 10,
        "node/comments/7764b6cb964ef8c481f3c348b76c6980e1e4f977#18460749": 39
      }
    },
    "2352663": {
      "id": "2352663",
      "login": "targos",
      "words": {
        "node/pulls/7920#72883310": 2,
        "node/pulls/7920#72883311": 1,
        "node/pulls/7920#236349725": 18
      }
    },
    "3502395": {
      "id": "3502395",
      "login": "rafis",
      "words": {
        "node-v0.x-archive/pulls/4666#236343997": 26,
        "node-v0.x-archive/pulls/4666#236380944": 16
      }
    },
    "4865608": {
      "id": "4865608",
      "login": "delvedor",
      "words": {
        "installer/pulls/26#236366242": 45
      }
    },
    "4925744": {
      "id": "4925744",
      "login": "Slayer95",
      "words": {
        "node/pulls/7920#72892495": 13
      }
    },
    "4949308": {
      "id": "4949308",
      "login": "sorinh",
      "words": {
        "node/pulls/7895#236360802": 20
      }
    },
    "6357744": {
      "id": "6357744",
      "login": "chadsfatherlali",
      "words": {
        "node-gyp/pulls/809#236388322": 272
      }
    },
    "20158340": {
      "id": "20158340",
      "login": "PaulTsai20160627",
      "words": {
        "node/issues/7921": 100,
        "node/pulls/7921#236345575": 6,
        "help/issues/235": 100,
        "help/pulls/235#236354025": 18,
        "help/pulls/235#236354632": 186,
        "help/pulls/235#236354732": 26,
        "help/pulls/235#236354769": 37,
        "help/pulls/235#236354779": 38,
        "help/pulls/235#236354797": 38,
        "help/pulls/235#236354826": 83
      },
      "opened": [
        "node/issues/7921",
        "help/issues/235"
      ],
      "closed": [
        "node/issues/7921"
      ]
    },
    "20266801": {
      "id": "20266801",
      "login": "arielnetanya",
      "words": {
        "node-gyp/issues/1003": 282
      },
      "opened": [
        "node-gyp/issues/1003"
      ]
    },
    "20699254": {
      "id": "20699254",
      "login": "suplch",
      "words": {
        "node/issues/7918": 91
      },
      "opened": [
        "node/issues/7918"
      ],
      "closed": [
        "node/issues/7918"
      ]
    }
  }
}