{
"579":{"login":"mikeal"},
"2289":{"login":"zeke"},
"2781":{"login":"chorrell"},
"4303":{"login":"jdalton"},
"4322":{"login":"dshaw"},
"5750":{"login":"benjamn"},
"9287":{"login":"isaacs"},
"13352":{"login":"cpojer"},
"15843":{"login":"dirceu"},
"15952":{"login":"lance"},
"17535":{"login":"zkat"},
"17978":{"login":"rmg"},
"20188":{"login":"tehsenaus"},
"20219":{"login":"conradwt"},
"32551":{"login":"davglass"},
"37303":{"login":"chrisdickinson"},
"39992":{"login":"gr2m"},
"40265":{"login":"tylersmalley"},
"45469":{"login":"ljharb"},
"52195":{"login":"mcollina"},
"54666":{"login":"mscdex"},
"66357":{"login":"ncopa"},
"67512":{"login":"dougwilson"},
"79017":{"login":"ofrobots"},
"90898":{"login":"wraithan"},
"96150":{"login":"dfabulich"},
"101553":{"login":"fhinkel"},
"106903":{"login":"mdlavin"},
"110455":{"login":"bengl"},
"115237":{"login":"silverwind"},
"116866":{"login":"joega"},
"119231":{"login":"rsp"},
"125466":{"login":"sejoker"},
"126482":{"login":"brycebaril"},
"134460":{"login":"joaocgreis"},
"141167":{"login":"scottgonzalez"},
"153481":{"login":"fhemberger"},
"156080":{"login":"cscott"},
"156867":{"login":"Krinkle"},
"170023":{"login":"DannyNemer"},
"173559":{"login":"auchenberg"},
"176984":{"login":"jbergstroem"},
"178512":{"login":"jfromaniello"},
"189580":{"login":"LinusU"},
"194609":{"login":"bcoe"},
"195826":{"login":"jeisinger"},
"205760":{"login":"kemitchell"},
"218257":{"login":"piscisaureus"},
"234659":{"login":"bmeck"},
"238531":{"login":"indutny"},
"255273":{"login":"matejv1"},
"265896":{"login":"pesho"},
"275871":{"login":"bnoordhuis"},
"287917":{"login":"eugeneo"},
"289174":{"login":"trevnorris"},
"291301":{"login":"ChALkeR"},
"304070":{"login":"jclulow"},
"312966":{"login":"mbroadst"},
"316498":{"login":"akira-cn"},
"317464":{"login":"saghul"},
"321966":{"login":"timkuijsten"},
"327019":{"login":"JacksonTian"},
"334851":{"login":"btd"},
"350686":{"login":"develar"},
"359239":{"login":"shiftkey"},
"361327":{"login":"DimitryDushkin"},
"365816":{"login":"peresleguine"},
"367936":{"login":"mhart"},
"369698":{"login":"avoidwork"},
"376661":{"login":"mafintosh"},
"390146":{"login":"outsideris"},
"405222":{"login":"listochkin"},
"406975":{"login":"jwulf"},
"410087":{"login":"TomFreudenberg"},
"414752":{"login":"matthew-dean"},
"416585":{"login":"olalonde"},
"432351":{"login":"danbev"},
"432707":{"login":"TDA"},
"439929":{"login":"jasnell"},
"441346":{"login":"geek"},
"444316":{"login":"tracker1"},
"469365":{"login":"zbjornson"},
"474587":{"login":"ilkkao"},
"495647":{"login":"rvagg"},
"498775":{"login":"TheAlphaNerd"},
"501424":{"login":"mastoj"},
"502396":{"login":"bnb"},
"505333":{"login":"AndreasMadsen"},
"509375":{"login":"naugtur"},
"520566":{"login":"iyakexi"},
"523141":{"login":"niftylettuce"},
"532688":{"login":"davepacheco"},
"557590":{"login":"RReverser"},
"572969":{"login":"kamn"},
"579928":{"login":"xzyfer"},
"606566":{"login":"zenoway"},
"613320":{"login":"vincentwoo"},
"617235":{"login":"emilyrose"},
"617481":{"login":"domenic"},
"628445":{"login":"panicbit"},
"631240":{"login":"ronkorving"},
"639601":{"login":"zcbenz"},
"649835":{"login":"ploxiln"},
"657552":{"login":"sandro-pasquali"},
"665754":{"login":"SomeoneWeird"},
"676289":{"login":"Jeff-Lewis"},
"677994":{"login":"evanlucas"},
"696611":{"login":"thefourtheye"},
"704514":{"login":"jcollum"},
"715626":{"login":"dsoprea"},
"718899":{"login":"Trott"},
"733364":{"login":"KenanY"},
"733877":{"login":"julianduque"},
"739813":{"login":"williamkapke"},
"744035":{"login":"ben-page"},
"767105":{"login":"ryanmurakami"},
"772595":{"login":"tasoss"},
"782880":{"login":"shigeki"},
"783424":{"login":"lifubang"},
"811047":{"login":"misterdjules"},
"825732":{"login":"yokomotod"},
"837040":{"login":"clausreinke"},
"850871":{"login":"NathanaelA"},
"853977":{"login":"yous"},
"855219":{"login":"srl295"},
"867842":{"login":"piccoloaiutante"},
"885648":{"login":"Qix-"},
"890329":{"login":"mlippautz"},
"894822":{"login":"dzlk"},
"899444":{"login":"addaleax"},
"914122":{"login":"martinheidegger"},
"968267":{"login":"Starefossen"},
"973545":{"login":"ankakusu"},
"983798":{"login":"iarna"},
"984304":{"login":"sylus"},
"988441":{"login":"seishun"},
"1018196":{"login":"nojvek"},
"1056976":{"login":"Gottox"},
"1063255":{"login":"techjeffharris"},
"1084056":{"login":"santigimeno"},
"1093990":{"login":"Fishrock123"},
"1106823":{"login":"NoelAbrahams"},
"1122386":{"login":"pmed"},
"1128607":{"login":"calvinmetcalf"},
"1131464":{"login":"mwain"},
"1137314":{"login":"azat-co"},
"1141386":{"login":"nebrius"},
"1150613":{"login":"RanzQ"},
"1177323":{"login":"gamtiq"},
"1177542":{"login":"meteatamel"},
"1226256":{"login":"yunong"},
"1231635":{"login":"phillipj"},
"1245785":{"login":"greenboxal"},
"1272762":{"login":"mike442144"},
"1277095":{"login":"Dmitry-Me"},
"1291228":{"login":"mariuszgola"},
"1296500":{"login":"lijunle"},
"1309053":{"login":"kiddkai"},
"1311919":{"login":"Spetnik"},
"1315533":{"login":"benjamingr"},
"1319181":{"login":"artemruts"},
"1333469":{"login":"tomruttle"},
"1340074":{"login":"diosney"},
"1347002":{"login":"xtaltas"},
"1356314":{"login":"stefanmb"},
"1386719":{"login":"aubergine10"},
"1426799":{"login":"felixrieseberg"},
"1443911":{"login":"lpinca"},
"1485909":{"login":"matthewloring"},
"1503976":{"login":"vinniefalco"},
"1622515":{"login":"princejwesley"},
"1625870":{"login":"orangemocha"},
"1702755":{"login":"nicosommi"},
"1742880":{"login":"flexiblefactory"},
"1760238":{"login":"ashalaenko"},
"1773260":{"login":"lordKnighton"},
"1778730":{"login":"thebergamo"},
"1823839":{"login":"nickdesaulniers"},
"1878740":{"login":"carantes"},
"1898413":{"login":"alexlamsl"},
"1906839":{"login":"cbuteau"},
"1915098":{"login":"robmusial"},
"1981088":{"login":"hackygolucky"},
"2054772":{"login":"Schniz"},
"2067616":{"login":"NawarA"},
"2135202":{"login":"talyaacov"},
"2236437":{"login":"gerardtoko"},
"2291463":{"login":"hashseed"},
"2329683":{"login":"davedoesdev"},
"2338703":{"login":"ChuckLangford"},
"2352663":{"login":"targos"},
"2377664":{"login":"sonewman"},
"2452620":{"login":"mjsalinger"},
"2512748":{"login":"cjihrig"},
"2533361":{"login":"JerryFox1"},
"2552507":{"login":"fluggo"},
"2607556":{"login":"SteveyPugs"},
"2620674":{"login":"bricss"},
"2645436":{"login":"codygustafson"},
"2785744":{"login":"ilfroloff"},
"2993861":{"login":"vkurchatkin"},
"3030172":{"login":"kazikai"},
"3277629":{"login":"rupamkhaitan"},
"3459374":{"login":"denysdovhan"},
"3506172":{"login":"mkozjak"},
"3625244":{"login":"ghaiklor"},
"3625961":{"login":"mcdonnelldean"},
"3760840":{"login":"rayshan"},
"3869412":{"login":"jfmengels"},
"3872744":{"login":"zetsingithub"},
"3899684":{"login":"eljefedelrodeodeljefe"},
"3929632":{"login":"Avinash-Raj"},
"3967972":{"login":"claudiorodriguez"},
"4017750":{"login":"oebspm"},
"4057921":{"login":"saschaarthur"},
"4103081":{"login":"kkoopa"},
"4134127":{"login":"sokoow"},
"4275075":{"login":"z0nk"},
"4295997":{"login":"rscharfer"},
"4309494":{"login":"rvnath"},
"4416545":{"login":"hackcode93"},
"4421720":{"login":"joshgav"},
"4831315":{"login":"Unterdrucker"},
"4865608":{"login":"delvedor"},
"4954074":{"login":"todojs"},
"4962589":{"login":"hnhegde"},
"4965093":{"login":"calibr"},
"5035902":{"login":"JungMinu"},
"5108906":{"login":"vitaly-t"},
"5177920":{"login":"suryagh"},
"5234060":{"login":"QianJin2013"},
"5259935":{"login":"Drenmi"},
"5273970":{"login":"jamr-ron"},
"5324913":{"login":"renambot-uic"},
"5347038":{"login":"Salakar"},
"5408109":{"login":"ajinkya007"},
"5438027":{"login":"andrasq"},
"5470583":{"login":"RainingChain"},
"5518550":{"login":"sergei-maertens"},
"5545474":{"login":"Awk34"},
"5550520":{"login":"r1b"},
"5832730":{"login":"rus0000"},
"6046654":{"login":"adam-beck"},
"6078550":{"login":"ore"},
"6098160":{"login":"BlackYoup"},
"6316590":{"login":"stevemao"},
"6354455":{"login":"italoacasas"},
"6443532":{"login":"bogdanvlviv"},
"6447530":{"login":"gireeshpunathil"},
"6628505":{"login":"cbfiddle"},
"6743214":{"login":"sunnee5150"},
"6907399":{"login":"thekemkid"},
"6917800":{"login":"robertchiras"},
"7109350":{"login":"horpto"},
"7146748":{"login":"classfellow"},
"7190422":{"login":"natorion"},
"7310875":{"login":"ColinChen2"},
"7537811":{"login":"CowLoverSecret"},
"8008055":{"login":"damirka"},
"8010038":{"login":"cdnadmin"},
"8067371":{"login":"napiera"},
"8369156":{"login":"amanisky"},
"8389594":{"login":"munyirik"},
"8600635":{"login":"chacent"},
"8627403":{"login":"zaynv"},
"8645887":{"login":"kristianjaeger"},
"8656098":{"login":"sttk"},
"8702326":{"login":"mike-kaufman"},
"8747500":{"login":"mlick"},
"9011953":{"login":"rbaprado"},
"9271436":{"login":"strarsis"},
"9373002":{"login":"mhdawson"},
"9503227":{"login":"tejkumar51"},
"9932290":{"login":"s100"},
"9937771":{"login":"AndrewPardoe"},
"9964060":{"login":"eddysant"},
"10103531":{"login":"gladys123"},
"10350212":{"login":"Arch-Mage"},
"10435209":{"login":"tarungarg546"},
"10704816":{"login":"sung-su"},
"11040896":{"login":"hanu412"},
"11084415":{"login":"maksymseleznov"},
"11534528":{"login":"esh009"},
"11720107":{"login":"beat-at-hartwig"},
"11782089":{"login":"fallingarrow"},
"11861955":{"login":"jianchun"},
"11883306":{"login":"kadir003"},
"12057627":{"login":"aruneshchandra"},
"12059066":{"login":"agarwal-sandeep"},
"12488060":{"login":"kunalspathak"},
"13033429":{"login":"mingyu-lee"},
"13361745":{"login":"Dilip9922"},
"13891170":{"login":"mik-jozef"},
"14981026":{"login":"gareth-ellis"},
"15069963":{"login":"H3lmaster"},
"15373625":{"login":"malpacasville"},
"15724278":{"login":"vsenko"},
"15857768":{"login":"blazekas"},
"15943089":{"login":"gibm"},
"16054109":{"login":"PAY-IT-FORWARD"},
"16335744":{"login":"samarthRT"},
"16412075":{"login":"116356754"},
"16545322":{"login":"MrQubo"},
"16601861":{"login":"almesh"},
"16722535":{"login":"rnchamberlain"},
"16800950":{"login":"endencia"},
"17704638":{"login":"bzoz"},
"18704287":{"login":"lijunqin"},
"18708370":{"login":"Flarna"},
"19684110":{"login":"hossein1991b"},
"19761566":{"login":"acb017"},
"19973729":{"login":"lwhoho"},
"19983178":{"login":"ipurdy"},
"20172108":{"login":"gezzz"},
"20201756":{"login":"Ksaelan"}
}